psdm_analysis/__init__.py
psdm_analysis/analysis/__init__.py
psdm_analysis/analysis/calc.py
psdm_analysis/analysis/grid.py
psdm_analysis/conversion/__init__.py
psdm_analysis/conversion/pandapower.py
psdm_analysis/errors.py
psdm_analysis/io/__init__.py
psdm_analysis/io/utils.py
psdm_analysis/models/__init__.py
psdm_analysis/models/enums.py
psdm_analysis/models/gwr.py
psdm_analysis/models/input/__init__.py
psdm_analysis/models/input/connector/__init__.py
psdm_analysis/models/input/connector/connector.py
psdm_analysis/models/input/connector/lines.py
psdm_analysis/models/input/connector/switches.py
psdm_analysis/models/input/connector/transformer.py
psdm_analysis/models/input/container/__init__.py
psdm_analysis/models/input/container/grid.py
psdm_analysis/models/input/container/mixins.py
psdm_analysis/models/input/container/participants.py
psdm_analysis/models/input/container/raw_grid.py
psdm_analysis/models/input/entity.py
psdm_analysis/models/input/node.py
psdm_analysis/models/input/participant/__init__.py
psdm_analysis/models/input/participant/bm.py
psdm_analysis/models/input/participant/charging.py
psdm_analysis/models/input/participant/em.py
psdm_analysis/models/input/participant/evcs.py
psdm_analysis/models/input/participant/evs.py
psdm_analysis/models/input/participant/fixed_feed_in.py
psdm_analysis/models/input/participant/hp.py
psdm_analysis/models/input/participant/load.py
psdm_analysis/models/input/participant/participant.py
psdm_analysis/models/input/participant/pv.py
psdm_analysis/models/input/participant/storage.py
psdm_analysis/models/input/participant/wec.py
psdm_analysis/models/primary_data.py
psdm_analysis/models/result/__init__.py
psdm_analysis/models/result/container/__init__.py
psdm_analysis/models/result/container/grid.py
psdm_analysis/models/result/container/participants.py
psdm_analysis/models/result/entity.py
psdm_analysis/models/result/flex_option.py
psdm_analysis/models/result/grid/__init__.py
psdm_analysis/models/result/grid/connector.py
psdm_analysis-0.1.8.dist-info/LICENSE
psdm_analysis-0.1.8.dist-info/METADATA
psdm_analysis-0.1.8.dist-info/WHEEL
psdm_analysis-0.1.8.dist-info/RECORD
