Metadata-Version: 2.1
Name: psdm-analysis
Version: 0.1.8
Summary: 
Author: Thomas Oberliessen
Author-email: thomas.oberliessen@googlemail.com
Requires-Python: >3.10,<3.12
Classifier: Programming Language :: Python :: 3
Classifier: Programming Language :: Python :: 3.11
Requires-Dist: jupyter (>=1.0.0,<2.0.0)
Requires-Dist: matplotlib (>=3.6.0,<4.0.0)
Requires-Dist: networkx (>=3.1,<4.0)
Requires-Dist: numpy (>=1.24.1,<2.0.0)
Requires-Dist: openpyxl (>=3.1.2,<4.0.0)
Requires-Dist: pandas (==2.0.1)
Requires-Dist: plotly (>=5.6.0,<6.0.0)
Requires-Dist: pyarrow (>=11.0.0,<12.0.0)
Requires-Dist: python-dotenv (>=1.0.0,<2.0.0)
Requires-Dist: requests (>=2.27.1,<3.0.0)
Requires-Dist: scipy (>=1.10.0,<2.0.0)
Requires-Dist: seaborn (>=0.12.1,<0.13.0)
Requires-Dist: shapely (>=2.0.1,<3.0.0)
